cdktf_cdktf_provider_aws/__init__.py
cdktf_cdktf_provider_aws/py.typed
cdktf_cdktf_provider_aws/_jsii/__init__.py
cdktf_cdktf_provider_aws/_jsii/provider-aws@14.0.2.jsii.tgz
cdktf_cdktf_provider_aws/accessanalyzer_analyzer/__init__.py
cdktf_cdktf_provider_aws/accessanalyzer_archive_rule/__init__.py
cdktf_cdktf_provider_aws/account_alternate_contact/__init__.py
cdktf_cdktf_provider_aws/acm_certificate/__init__.py
cdktf_cdktf_provider_aws/acm_certificate_validation/__init__.py
cdktf_cdktf_provider_aws/acmpca_certificate/__init__.py
cdktf_cdktf_provider_aws/acmpca_certificate_authority/__init__.py
cdktf_cdktf_provider_aws/acmpca_certificate_authority_certificate/__init__.py
cdktf_cdktf_provider_aws/acmpca_permission/__init__.py
cdktf_cdktf_provider_aws/acmpca_policy/__init__.py
cdktf_cdktf_provider_aws/alb/__init__.py
cdktf_cdktf_provider_aws/alb_listener/__init__.py
cdktf_cdktf_provider_aws/alb_listener_certificate/__init__.py
cdktf_cdktf_provider_aws/alb_listener_rule/__init__.py
cdktf_cdktf_provider_aws/alb_target_group/__init__.py
cdktf_cdktf_provider_aws/alb_target_group_attachment/__init__.py
cdktf_cdktf_provider_aws/ami/__init__.py
cdktf_cdktf_provider_aws/ami_copy/__init__.py
cdktf_cdktf_provider_aws/ami_from_instance/__init__.py
cdktf_cdktf_provider_aws/ami_launch_permission/__init__.py
cdktf_cdktf_provider_aws/amplify_app/__init__.py
cdktf_cdktf_provider_aws/amplify_backend_environment/__init__.py
cdktf_cdktf_provider_aws/amplify_branch/__init__.py
cdktf_cdktf_provider_aws/amplify_domain_association/__init__.py
cdktf_cdktf_provider_aws/amplify_webhook/__init__.py
cdktf_cdktf_provider_aws/api_gateway_account/__init__.py
cdktf_cdktf_provider_aws/api_gateway_api_key/__init__.py
cdktf_cdktf_provider_aws/api_gateway_authorizer/__init__.py
cdktf_cdktf_provider_aws/api_gateway_base_path_mapping/__init__.py
cdktf_cdktf_provider_aws/api_gateway_client_certificate/__init__.py
cdktf_cdktf_provider_aws/api_gateway_deployment/__init__.py
cdktf_cdktf_provider_aws-14.0.2.dist-info/LICENSE
cdktf_cdktf_provider_aws-14.0.2.dist-info/METADATA
cdktf_cdktf_provider_aws-14.0.2.dist-info/WHEEL
cdktf_cdktf_provider_aws-14.0.2.dist-info/top_level.txt
cdktf_cdktf_provider_aws-14.0.2.dist-info/RECORD
