Metadata-Version: 2.1
Name: cdktf-cdktf-provider-aws
Version: 14.0.2
Summary: Prebuilt aws Provider for Terraform CDK (cdktf)
Home-page: https://github.com/cdktf/cdktf-provider-aws.git
Author: HashiCorp
License: MPL-2.0
Project-URL: Source, https://github.com/cdktf/cdktf-provider-aws.git
Classifier: Intended Audience :: Developers
Classifier: Operating System :: OS Independent
Classifier: Programming Language :: JavaScript
Classifier: Programming Language :: Python :: 3 :: Only
Classifier: Programming Language :: Python :: 3.7
Classifier: Programming Language :: Python :: 3.8
Classifier: Programming Language :: Python :: 3.9
Classifier: Programming Language :: Python :: 3.10
Classifier: Programming Language :: Python :: 3.11
Classifier: Typing :: Typed
Classifier: Development Status :: 5 - Production/Stable
Classifier: License :: OSI Approved
Requires-Python: ~=3.7
License-File: LICENSE
Requires-Dist: cdktf (<0.17.0,>=0.16.0)
Requires-Dist: constructs (<11.0.0,>=10.0.0)
Requires-Dist: jsii (<2.0.0,>=1.80.0)
Requires-Dist: publication (>=0.0.3)
Requires-Dist: typeguard (~=2.13.3)
